contentgrid_hal_client/__init__.py
contentgrid_hal_client/exceptions.py
contentgrid_hal_client/hal.py
contentgrid_hal_client/hal_forms.py
contentgrid_hal_client/py.typed
contentgrid_hal_client/security.py
contentgrid_hal_client/token_utils.py
contentgrid_hal_client-0.2.2.dist-info/licenses/LICENSE
contentgrid_hal_client-0.2.2.dist-info/METADATA
contentgrid_hal_client-0.2.2.dist-info/WHEEL
contentgrid_hal_client-0.2.2.dist-info/top_level.txt
contentgrid_hal_client-0.2.2.dist-info/RECORD
