Metadata-Version: 2.4
Name: contentgrid-hal-client
Version: 0.2.2
Summary: Python Client for interacting with HAL-forms application
Author-email: Ranec Belpaire <ranec.belpaire@xenit.eu>
License: Copyright 2024 Xenit Solutions
Classifier: Development Status :: 4 - Beta
Classifier: Operating System :: OS Independent
Classifier: Programming Language :: Python :: 3
Requires-Python: >=3.5
License-File: LICENSE
Requires-Dist: requests<3,>=2.20.0
Requires-Dist: uri-template<2
Requires-Dist: hyperlink>=21
Requires-Dist: pydantic<3,>=2.0.0
Dynamic: license-file
